AUTHORS.rst
CHANGELOG.rst
LICENSE
MANIFEST.in
README.rst
setup.py
django_preferences.egg-info/PKG-INFO
django_preferences.egg-info/SOURCES.txt
django_preferences.egg-info/dependency_links.txt
django_preferences.egg-info/requires.txt
django_preferences.egg-info/top_level.txt
preferences/__init__.py
preferences/__init__.pyc
preferences/admin.py
preferences/admin.pyc
preferences/context_processors.py
preferences/context_processors.pyc
preferences/managers.py
preferences/managers.pyc
preferences/models.py
preferences/models.pyc
preferences/__pycache__/__init__.cpython-36.pyc
preferences/__pycache__/__init__.cpython-37.pyc
preferences/__pycache__/admin.cpython-36.pyc
preferences/__pycache__/admin.cpython-37.pyc
preferences/__pycache__/context_processors.cpython-36.pyc
preferences/__pycache__/context_processors.cpython-37.pyc
preferences/__pycache__/managers.cpython-36.pyc
preferences/__pycache__/managers.cpython-37.pyc
preferences/__pycache__/models.cpython-36.pyc
preferences/__pycache__/models.cpython-37.pyc
preferences/migrations/0001_initial.py
preferences/migrations/0001_initial.pyc
preferences/migrations/0002_auto_20181220_0803.py
preferences/migrations/0002_auto_20181220_0803.pyc
preferences/migrations/__init__.py
preferences/migrations/__init__.pyc
preferences/migrations/__pycache__/0001_initial.cpython-36.pyc
preferences/migrations/__pycache__/0001_initial.cpython-37.pyc
preferences/migrations/__pycache__/0002_auto_20181220_0803.cpython-36.pyc
preferences/migrations/__pycache__/0002_auto_20181220_0803.cpython-37.pyc
preferences/migrations/__pycache__/__init__.cpython-36.pyc
preferences/migrations/__pycache__/__init__.cpython-37.pyc
preferences/tests/__init__.py
preferences/tests/__init__.pyc
preferences/tests/admin.py
preferences/tests/admin.pyc
preferences/tests/models.py
preferences/tests/models.pyc
preferences/tests/test_all.py
preferences/tests/test_all.pyc
preferences/tests/urls.py
preferences/tests/urls.pyc
preferences/tests/__pycache__/__init__.cpython-36.pyc
preferences/tests/__pycache__/__init__.cpython-37.pyc
preferences/tests/__pycache__/admin.cpython-36.pyc
preferences/tests/__pycache__/admin.cpython-37.pyc
